sktimeutils/__init__.py
sktimeutils/_version.py
sktimeutils/datetime64.py
sktimeutils/eci.py
sktimeutils/juliandate.py
sktimeutils/mjd.py
sktimeutils/tests/__init__.py
sktimeutils/tests/test_conversions.py
sktimeutils/tests/test_jd.py
sktimeutils/tests/test_mjd.py
sktimeutils-2.0.9.dist-info/licenses/LICENSE
sktimeutils-2.0.9.dist-info/METADATA
sktimeutils-2.0.9.dist-info/WHEEL
sktimeutils-2.0.9.dist-info/top_level.txt
sktimeutils-2.0.9.dist-info/RECORD
