Metadata-Version: 2.4
Name: sktimeutils
Version: 2.0.9
Summary: Array based, Universal Time conversion functions and classes  used by usask-arg software
Author-email: Nick Lloyd <nick.lloyd@usask.ca>
License: MIT
Classifier: Development Status :: 4 - Beta
Classifier: License :: OSI Approved :: MIT License
Classifier: Programming Language :: Python :: 3 :: Only
Classifier: Programming Language :: Python :: 3.7
Classifier: Programming Language :: Python :: 3.8
Classifier: Programming Language :: Python :: 3.9
Classifier: Programming Language :: Python :: 3.10
Classifier: Programming Language :: Python :: 3.11
Classifier: Programming Language :: Python :: 3.12
Classifier: Programming Language :: Python :: 3.13
Requires-Python: >=3.7
License-File: LICENSE
Requires-Dist: numpy
Requires-Dist: jdcal
Requires-Dist: astropy
Dynamic: license-file
